gsozo_pkg/__init__.py
gsozo_pkg/microsoft/__init__.py
gsozo_pkg/microsoft/outlook/__init__.py
gsozo_pkg/microsoft/outlook/appointment.py
gsozo_pkg/microsoft/outlook/email.py
gsozo_pkg/pipedrive/__init__.py
gsozo_pkg/pipedrive/_backup.py
gsozo_pkg/pipedrive/_manipulator.py
gsozo_pkg/pipedrive/_sanitizer.py
gsozo_pkg/pipedrive/activities.py
gsozo_pkg/pipedrive/client.py
gsozo_pkg/pipedrive/deals.py
gsozo_pkg/pipedrive/files.py
gsozo_pkg/pipedrive/organizations.py
gsozo_pkg/pipedrive/persons.py
gsozo_pkg/pipedrive/stages.py
gsozo_pkg/xp_api/__init__.py
gsozo_pkg/xp_api/_investment_funds.py
gsozo_pkg/xp_api/_onboarding_rede_customers.py
gsozo_pkg/xp_api/_pension_funds.py
gsozo_pkg/xp_api/_rede_advisors.py
gsozo_pkg/xp_api/_rede_customer.py
gsozo_pkg/xp_api/client.py
gsozo_pkg-0.0.7.dist-info/METADATA
gsozo_pkg-0.0.7.dist-info/WHEEL
gsozo_pkg-0.0.7.dist-info/licenses/LICENSE
gsozo_pkg-0.0.7.dist-info/RECORD
