Metadata-Version: 2.1
Name: gsozo-pkg
Version: 0.0.7
Summary: Gsozo PKG
Author-email: Tecnologia Grupo SOZO <tecnologia@gruposozo.com.br>
License-File: LICENSE
Classifier: License :: OSI Approved :: MIT License
Classifier: Operating System :: OS Independent
Classifier: Programming Language :: Python :: 3
Requires-Python: >=3.8
Requires-Dist: jinja2>=3.1.2
Requires-Dist: loguru>=0.7.2
Requires-Dist: numpy<=1.26.2,>=1.24.4
Requires-Dist: pandas<=2.1.4,>=2.0.3
Requires-Dist: pipedrive-python-lib>=1.2.3
Requires-Dist: requests>=2.31.0
Requires-Dist: sqlalchemy>=1.4.9
Requires-Dist: tqdm>=4.66.1
